.gitignore
README.txt
setup.py
Paste-1.7.2-py2.6.egg/EGG-INFO/PKG-INFO
Paste-1.7.2-py2.6.egg/EGG-INFO/SOURCES.txt
Paste-1.7.2-py2.6.egg/EGG-INFO/dependency_links.txt
Paste-1.7.2-py2.6.egg/EGG-INFO/entry_points.txt
Paste-1.7.2-py2.6.egg/EGG-INFO/namespace_packages.txt
Paste-1.7.2-py2.6.egg/EGG-INFO/not-zip-safe
Paste-1.7.2-py2.6.egg/EGG-INFO/requires.txt
Paste-1.7.2-py2.6.egg/EGG-INFO/top_level.txt
Paste-1.7.2-py2.6.egg/paste/__init__.py
Paste-1.7.2-py2.6.egg/paste/__init__.pyc
Paste-1.7.2-py2.6.egg/paste/cascade.py
Paste-1.7.2-py2.6.egg/paste/cascade.pyc
Paste-1.7.2-py2.6.egg/paste/cgiapp.py
Paste-1.7.2-py2.6.egg/paste/cgiapp.pyc
Paste-1.7.2-py2.6.egg/paste/cgitb_catcher.py
Paste-1.7.2-py2.6.egg/paste/cgitb_catcher.pyc
Paste-1.7.2-py2.6.egg/paste/config.py
Paste-1.7.2-py2.6.egg/paste/config.pyc
Paste-1.7.2-py2.6.egg/paste/errordocument.py
Paste-1.7.2-py2.6.egg/paste/errordocument.pyc
Paste-1.7.2-py2.6.egg/paste/fileapp.py
Paste-1.7.2-py2.6.egg/paste/fileapp.pyc
Paste-1.7.2-py2.6.egg/paste/fixture.py
Paste-1.7.2-py2.6.egg/paste/fixture.pyc
Paste-1.7.2-py2.6.egg/paste/flup_session.py
Paste-1.7.2-py2.6.egg/paste/flup_session.pyc
Paste-1.7.2-py2.6.egg/paste/gzipper.py
Paste-1.7.2-py2.6.egg/paste/gzipper.pyc
Paste-1.7.2-py2.6.egg/paste/httpexceptions.py
Paste-1.7.2-py2.6.egg/paste/httpexceptions.pyc
Paste-1.7.2-py2.6.egg/paste/httpheaders.py
Paste-1.7.2-py2.6.egg/paste/httpheaders.pyc
Paste-1.7.2-py2.6.egg/paste/httpserver.py
Paste-1.7.2-py2.6.egg/paste/httpserver.pyc
Paste-1.7.2-py2.6.egg/paste/lint.py
Paste-1.7.2-py2.6.egg/paste/lint.pyc
Paste-1.7.2-py2.6.egg/paste/modpython.py
Paste-1.7.2-py2.6.egg/paste/modpython.pyc
Paste-1.7.2-py2.6.egg/paste/pony.py
Paste-1.7.2-py2.6.egg/paste/pony.pyc
Paste-1.7.2-py2.6.egg/paste/progress.py
Paste-1.7.2-py2.6.egg/paste/progress.pyc
Paste-1.7.2-py2.6.egg/paste/proxy.py
Paste-1.7.2-py2.6.egg/paste/proxy.pyc
Paste-1.7.2-py2.6.egg/paste/recursive.py
Paste-1.7.2-py2.6.egg/paste/recursive.pyc
Paste-1.7.2-py2.6.egg/paste/registry.py
Paste-1.7.2-py2.6.egg/paste/registry.pyc
Paste-1.7.2-py2.6.egg/paste/reloader.py
Paste-1.7.2-py2.6.egg/paste/reloader.pyc
Paste-1.7.2-py2.6.egg/paste/request.py
Paste-1.7.2-py2.6.egg/paste/request.pyc
Paste-1.7.2-py2.6.egg/paste/response.py
Paste-1.7.2-py2.6.egg/paste/response.pyc
Paste-1.7.2-py2.6.egg/paste/session.py
Paste-1.7.2-py2.6.egg/paste/session.pyc
src/pasteFunBot.egg-info/PKG-INFO
src/pasteFunBot.egg-info/SOURCES.txt
src/pasteFunBot.egg-info/dependency_links.txt
src/pasteFunBot.egg-info/entry_points.txt
src/pasteFunBot.egg-info/not-zip-safe
src/pasteFunBot.egg-info/requires.txt
src/pasteFunBot.egg-info/top_level.txt
