Metadata-Version: 1.0
Name: pasteFunBot
Version: 0.1
Summary: Tool to build and test a complete project
Home-page: http://piers73600.github.com/pasteFunBot
Author: Piers(Pierre-Louis Davallon)
Author-email: pl.davallon@gmail.com
License: UNKNOWN
Keywords: funkload buildbot funbot pasteFunBot
Platform: UNKNOWN
